pyrealtime/__init__.py
pyrealtime/buffers.py
pyrealtime/decode_layer.py
pyrealtime/decorators.py
pyrealtime/filter_layers.py
pyrealtime/input_layers.py
pyrealtime/layer.py
pyrealtime/layer_manager.py
pyrealtime/network_layers.py
pyrealtime/nidaq.py
pyrealtime/pygame.py
pyrealtime/record_layer.py
pyrealtime/script_layers.py
pyrealtime/serial_layer.py
pyrealtime/subprocess.py
pyrealtime/utility_layers.py
pyrealtime/utils.py
pyrealtime/plotting/__init__.py
pyrealtime/plotting/base.py
pyrealtime/plotting/scatter.py
PyRealtime-0.1.13.dist-info/LICENSE
PyRealtime-0.1.13.dist-info/METADATA
PyRealtime-0.1.13.dist-info/WHEEL
PyRealtime-0.1.13.dist-info/top_level.txt
PyRealtime-0.1.13.dist-info/RECORD
