Metadata-Version: 2.1
Name: PyRealtime
Version: 0.1.13
Summary: A package for realtime data processing, including reading from serial ports and plotting.
Home-page: https://github.com/ewhitmire/pyrealtime
Author: Eric Whitmire
Author-email: emwhit@cs.washington.edu
License: MIT
Keywords: realtime,plotting,serialport,logging,pipeline
Platform: any
Requires-Dist: numpy
Requires-Dist: matplotlib
Provides-Extra: all
Requires-Dist: pyserial ; extra == 'all'
Requires-Dist: pygame ; extra == 'all'
Requires-Dist: scipy ; extra == 'all'
Provides-Extra: pygame
Requires-Dist: pygame ; extra == 'pygame'
Provides-Extra: serial
Requires-Dist: pyserial ; extra == 'serial'
